setup.py
zlshare/VERSION.txt
zlshare/__init__.py
zlshare/__init__.pyc
zlshare.egg-info/PKG-INFO
zlshare.egg-info/SOURCES.txt
zlshare.egg-info/dependency_links.txt
zlshare.egg-info/not-zip-safe
zlshare.egg-info/requires.txt
zlshare.egg-info/top_level.txt
zlshare/bond/__init__.py
zlshare/funcat/VERSION.txt
zlshare/funcat/__init__.py
zlshare/funcat/api.py
zlshare/funcat/context.py
zlshare/funcat/func.py
zlshare/funcat/helper.py
zlshare/funcat/indicators.py
zlshare/funcat/time_series.py
zlshare/funcat/utils.py
zlshare/funcat/data/__init__.py
zlshare/funcat/data/backend.py
zlshare/funcat/data/rqalpha_data_backend.py
zlshare/funcat/data/rqdata_data_backend.py
zlshare/funcat/data/tushare_backend.py
zlshare/funcat/data/zealink_data_backend.py
zlshare/fund/__init__.py
zlshare/futures/__init__.py
zlshare/stock/__init__.py
zlshare/stock/__init__.pyc
zlshare/stock/test.py
zlshare/stock/trading.py
zlshare/stock/trading.pyc
zlshare/stock/vars.py
zlshare/stock/vars.pyc
zlshare/utils/__init__.py
zlshare/utils/__init__.pyc
zlshare/utils/apiclient.py
zlshare/utils/netbase.py
zlshare/utils/netbase.pyc
zlshare/utils/vars.py
zlshare/utils/vars.pyc
zlshare/vtrade/__init__.py
zlshare/vtrade/__init__.pyc
zlshare/vtrade/vtrade.py
zlshare/vtrade/vtrade.pyc