Metadata-Version: 1.1
Name: zlshare
Version: 0.0.1
Summary: zlshare
Home-page: UNKNOWN
Author: Nathan Lu
Author-email: luqy@zealink.com
License: Apache License v2
Platform: UNKNOWN
Classifier: Programming Language :: Python
Classifier: Operating System :: Microsoft :: Windows
Classifier: Operating System :: Unix
Classifier: Programming Language :: Python :: 2.7
Classifier: Programming Language :: Python :: 3.4
Classifier: Programming Language :: Python :: 3.5
Classifier: Programming Language :: Python :: 3.6
